jkff_counter.v
module jkff(Q, J, K, clear, clk);
    input J, K, clear, clk;
    output reg Q;
    
    always @(posedge clk or negedge clear) begin
        if (!clear)
            Q <= 0;
        else if (J == 0 && K == 1)
            Q <= 0;
        else if (J == 1 && K == 0)
            Q <= 1;
        else if (J == 1 && K == 1)
            Q <= ~Q;
        // No need for an else case as Q will retain its value by default
    end
endmodule

// Synchronous Counter Module
module synchronous_counter(clear, clk, Q);
    input clear, clk;
    output [2:0] Q;
    
    // JK Flip-Flop instances
    jkff FF0(Q[0], ~Q[1], 1'b1, clear, clk);
    jkff FF1(Q[1], Q[0], 1'b1, clear, clk);
    jkff FF2(Q[2], Q[1] && ~Q[0], Q[1], clear, clk);
endmodule

jkff_counter_tb.v
`timescale 1ns/1ns
`include"jkff_counter.v"
module jkff_counter_tb;
reg clear,clk;
wire [2:0]Q;
synchronous_counter G0(clear,clk,Q);
always #10 clk=~clk;
initial
begin
clear=0;
clk=1;
#150 $finish;
end
initial
begin
$dumpfile("jkff_counter_tb.vcd");
$dumpvars(0,jkff_counter_tb);
$monitor($time,"clear=%b, Q=%3b",clear,Q);
#12 clear=1;
end
endmodule

jkff_counter_tb.vcd
$date
	Tue Oct  8 10:52:55 2024
$end
$version
	Icarus Verilog
$end
$timescale
	1ns
$end
$scope module jkff_counter_tb $end
$var wire 3 ! Q [2:0] $end
$var reg 1 " clear $end
$var reg 1 # clk $end
$scope module G0 $end
$var wire 1 " clear $end
$var wire 1 # clk $end
$var wire 3 $ Q [2:0] $end
$scope module FF0 $end
$var wire 1 % J $end
$var wire 1 & K $end
$var wire 1 " clear $end
$var wire 1 # clk $end
$var reg 1 ' Q $end
$upscope $end
$scope module FF1 $end
$var wire 1 ( J $end
$var wire 1 ) K $end
$var wire 1 " clear $end
$var wire 1 # clk $end
$var reg 1 * Q $end
$upscope $end
$scope module FF2 $end
$var wire 1 + J $end
$var wire 1 , K $end
$var wire 1 " clear $end
$var wire 1 # clk $end
$var reg 1 - Q $end
$upscope $end
$upscope $end
$upscope $end
$enddefinitions $end
#0
$dumpvars
0-
0,
0+
0*
1)
0(
0'
1&
1%
b0 $
1#
0"
b0 !
$end
#10
0#
#12
1"
#20
1(
b1 !
b1 $
1'
1#
#30
0#
#40
1+
0%
0(
1,
0'
b10 !
b10 $
1*
1#
#50
0#
#60
0+
1%
0,
1-
b100 !
b100 $
0*
1#
#70
0#
#80
1(
b101 !
b101 $
1'
1#
#90
0#
#100
1+
0%
1,
0(
1*
b110 !
b110 $
0'
1#
#110
0#
#120
0+
1%
0,
0*
b0 !
b0 $
0-
1#
#130
0#
#140
1(
b1 !
b1 $
1'
1#
