seq.v

module seq(clk, reset, x, z);
    input clk, reset, x;
    output reg z;
    output reg [2:0] cs, ns;

   
    parameter A = 3'b000;
    parameter B = 3'b001;
    parameter D = 3'b011;
    parameter F = 3'b010;
    parameter G = 3'b110;

   
    always @ (cs or x) begin
        case (cs)
            A: if (x) ns = B; else ns = F;
            B: if (x) ns = A; else ns = D;
            D: if (x) ns = A; else ns = G;
            F: if (x) ns = B; else ns = F; 
            G: if (x) ns = D; else ns = G; 
            default: ns = A;
        endcase
    end

   
    always @(posedge clk or posedge reset) begin
        if (reset)
            cs <= A;
        else
            cs <= ns;
    end


    always @ (cs or x) begin
        z = (cs[1] & ~cs[2] & ~x) || (cs[1] & ~cs[0] & x);
    end
endmodule

seq_tb.v
`timescale 1ns/1ns
`include "seq.v"
module seq_tb();
reg x,clk,reset;
wire z;
wire [2:0]y;
seq sc(x,clk,reset,z);
initial clk=0;
always #10 clk=~clk;
initial begin
$dumpfile("seq_tb.vcd");
$dumpvars(0,seq_tb);
reset=1;x=0;
#20 reset=0;x=1;
#20 x=0;
#20 x=1;
#20 x=0;
#20 x=1;
#100
$display("Test Complete");
$finish;
end
endmodule

seq_tb.vcd
$date
	Sat Oct  5 10:23:09 2024
$end
$version
	Icarus Verilog
$end
$timescale
	1ns
$end
$scope module seq_tb $end
$var wire 1 ! z $end
$var reg 1 " clk $end
$var reg 1 # reset $end
$var reg 1 $ x $end
$scope module sc $end
$var wire 1 $ clk $end
$var wire 1 " reset $end
$var wire 1 # x $end
$var reg 3 % cs [2:0] $end
$var reg 3 & ns [2:0] $end
$var reg 1 ! z $end
$upscope $end
$upscope $end
$enddefinitions $end
#0
$dumpvars
b0 &
bx %
0$
1#
0"
x!
$end
#10
b1 &
0!
b0 %
1"
#20
1!
b10 %
b10 &
0"
1$
0#
#30
0!
b0 %
1"
#40
0"
0$
#50
1"
#60
1!
b10 %
0"
1$
#70
0!
b0 %
1"
#80
0"
0$
#90
1"
#100
1!
b10 %
0"
1$
#110
0!
b0 %
1"
