seq_1010.v
module seq_1010(clk, reset, in, out);
input clk, reset,in;
output reg out;
output reg[1:0]cs,ns;
parameter s0=2'b00;
parameter s1=2'b01; 
parameter s2=2'b10;
parameter s3=2'b11;
always @(posedge clk or posedge reset)begin
if(reset)
	cs<=s0;
else
	cs<=ns;
end

always @(*)begin
case(cs)
s0: 
begin
	ns=in?s1:s0;
	out=1'b0;
end


s1:
begin 
	ns=in?s2:s1;
	out=1'b0;
end

s2:
begin
	ns=in?s0:s3;
	out=1'b0;
end
s3:
begin
	ns=in?s2:s1;
	out=in?1'b0:1'b1;
end

default: 
begin 
	ns=s0;
	out=1'b0;
end

endcase
end
endmodule

seq_1010_tb.v
`timescale 1ns/1ns
`include "seq_1010.v"

module seq_1010_tb();
reg clk,reset,in;
wire out;
wire [1:0]ns;
seq_1010 ss(clk,reset,in,out);
initial clk=0;
always #10 clk=~clk;
initial begin
$dumpfile("seq_1010_tb.vcd");
$dumpvars(0,seq_1010_tb);
reset=1;in=0;
#20 reset=0; in=1;
#20 in=1;
#20 in=0;
#20 in=1;
#20 in=0;
#20 in=1;
#20 in=1;
#20 in=0;
#20 in=1;
#20 in=0;
#20 in=1;
#20 in=0;
#100;
$display("Test Complete");
#160;
$finish;
end
endmodule

seq_1010_tb.vcd
$date
	Sat Oct  5 10:54:02 2024
$end
$version
	Icarus Verilog
$end
$timescale
	1ns
$end
$scope module seq_1010_tb $end
$var wire 1 ! out $end
$var reg 1 " clk $end
$var reg 1 # in $end
$var reg 1 $ reset $end
$scope module ss $end
$var wire 1 " clk $end
$var wire 1 # in $end
$var wire 1 $ reset $end
$var reg 2 % cs [1:0] $end
$var reg 2 & ns [1:0] $end
$var reg 1 ! out $end
$upscope $end
$upscope $end
$enddefinitions $end
#0
$dumpvars
b0 &
b0 %
1$
0#
0"
0!
$end
#10
1"
#20
b1 &
0"
1#
0$
#30
b10 &
b1 %
1"
#40
0"
#50
b0 &
b10 %
1"
#60
b11 &
0"
0#
#70
1!
b1 &
b11 %
1"
#80
0!
b10 &
0"
1#
#90
b0 &
b10 %
1"
#100
b11 &
0"
0#
#110
1!
b1 &
b11 %
1"
#120
0!
b10 &
0"
1#
#130
b0 &
b10 %
1"
#140
0"
#150
b1 &
b0 %
1"
#160
b0 &
0"
0#
#170
1"
#180
b1 &
0"
1#
#190
b10 &
b1 %
1"
#200
b1 &
0"
0#
#210
1"
#220
b10 &
0"
1#
#230
b0 &
b10 %
1"
#240
b11 &
0"
0#
#250
1!
b1 &
b11 %
1"
#260
0"
#270
0!
b1 %
1"
