Lab_3/mux16to1.v
module mux2to1 (a,b,sel,out);
 input a,b,sel;
 output reg out;
 always @(a,b,sel) begin
 case (sel)
 0:out=a;
 1:out=b;
 default: out=1'b0;
 endcase
 end
 endmodule
 
 module mux8to1(in, sel,out);
 input [7:0]in;
 input [2:0]sel;
output reg out;
 always @(in,sel)begin
 case(sel)
 0:out=in[0];
 1:out=in[1];
 2:out=in[2];
 3:out=in[3];
 4:out=in[4];
 5:out=in[5];
 6:out=in[6];
 7:out=in[7];
 default: out=1'b0;
 endcase
 end 
 endmodule
 
 module mux16to1(in,sel,out);
 input [15:0]in;
 input [3:0] sel;
output out;
 wire mux1_out,mux2_out;
 mux8to1 mux1(in[7:0],sel[2:0],mux1_out);
 mux8to1 mux2(in[15:8],sel[2:0],mux2_out);
 mux2to1 mux3(mux1_out, mux2_out,sel[3],out);
 endmodule

Lab_3/mux16to1_tb.v
`timescale 1ns/1ns
`include "mux16to1.v"
 module mux16to1_tb();
 reg [15:0]in;
 reg [3:0] sel;
 wire out;
 mux16to1 m16to1(in, sel,out);
 initial
 begin
 $dumpfile("mux16to1_tb.vcd");
 $dumpvars(0,mux16to1_tb);
 in=16'b1010101010101010;
 sel=4'b0000;
 #10;
  sel=4'b0001;
 #10;
  sel=4'b0010;
 #10;
  sel=4'b0011;
 #10;
  sel=4'b0100;
 #10;
  sel=4'b0101;
 #10;
  sel=4'b0110;
 #10;
  sel=4'b0111;
 #10;
  sel=4'b1000;
 #10;
  sel=4'b1001;
 #10;
  sel=4'b1010;
 #10;
  sel=4'b1011;
 #10;
  sel=4'b1100;
 #10;
  sel=4'b1101;
 #10;
 sel=4'b1110;
 #10;
 sel=4'b1111;
 #10;
 end
 endmodule

Lab_3/mux16to1_tb.vcd
$date
	Sat Aug 24 10:38:57 2024
$end
$version
	Icarus Verilog
$end
$timescale
	1ns
$end
$scope module mux16to1_tb $end
$var wire 1 ! out $end
$var reg 16 " in [15:0] $end
$var reg 4 # sel [3:0] $end
$scope module m16to1 $end
$var wire 16 $ in [15:0] $end
$var wire 4 % sel [3:0] $end
$var wire 1 ! out $end
$var wire 1 & mux2_out $end
$var wire 1 ' mux1_out $end
$scope module mux1 $end
$var wire 8 ( in [7:0] $end
$var wire 3 ) sel [2:0] $end
$var reg 1 ' out $end
$upscope $end
$scope module mux2 $end
$var wire 8 * in [7:0] $end
$var wire 3 + sel [2:0] $end
$var reg 1 & out $end
$upscope $end
$scope module mux3 $end
$var wire 1 ' a $end
$var wire 1 & b $end
$var wire 1 , sel $end
$var reg 1 ! out $end
$upscope $end
$upscope $end
$upscope $end
$enddefinitions $end
#0
$dumpvars
0,
b0 +
b10101010 *
b0 )
b10101010 (
0'
0&
b0 %
b1010101010101010 $
b0 #
b1010101010101010 "
0!
$end
#10
1!
1'
1&
b1 )
b1 +
b1 #
b1 %
#20
0!
0'
0&
b10 )
b10 +
b10 #
b10 %
#30
1!
1'
1&
b11 )
b11 +
b11 #
b11 %
#40
0!
0'
0&
b100 )
b100 +
b100 #
b100 %
#50
1!
1'
1&
b101 )
b101 +
b101 #
b101 %
#60
0!
0'
0&
b110 )
b110 +
b110 #
b110 %
#70
1!
1'
1&
b111 )
b111 +
b111 #
b111 %
#80
0!
0'
0&
b0 )
b0 +
1,
b1000 #
b1000 %
#90
1!
1'
1&
b1 )
b1 +
b1001 #
b1001 %
#100
0!
0'
0&
b10 )
b10 +
b1010 #
b1010 %
#110
1!
1'
1&
b11 )
b11 +
b1011 #
b1011 %
#120
0!
0'
0&
b100 )
b100 +
b1100 #
b1100 %
#130
1!
1'
1&
b101 )
b101 +
b1101 #
b1101 %
#140
0!
0'
0&
b110 )
b110 +
b1110 #
b1110 %
#150
1!
1'
1&
b111 )
b111 +
b1111 #
b1111 %
