Lab_5/graytobin.v
module mux8to1(s,in0,in1,in2,in3,in4,in5,in6,in7,out);
 input [2:0]s;
 input in0,in1,in2,in3,in4,in5,in6,in7;
 output reg out;
 always @ (*) begin
 case(s)
 0: out=in0;
 1: out=in1;
 2: out=in2;
 3: out=in3;
 4: out=in4;
 5: out=in5;
 6: out=in6;
 7: out=in7;
 default: out=in0;
 endcase
 end
 endmodule
 module graytobin(g,b);
 input [3:0]g;
 output [3:0]b;
 mux8to1 m1(g[3:0],0,0,0,0,1,1,1,1,b[3]);
 mux8to1 m2(g[3:0],0,0,1,1,1,1,0,0,b[2]);
 mux8to1 m3(g[3:0],0,1,1,0,1,0,0,1,b[1]);
 mux8to1 m4(g[3:0],g[0],~g[0],~g[0],g[0],~g[0],g[0],g[0],~g[0],b[0]);
 endmodule

Lab_5/graytobin_tb.v
`timescale 1ns/1ns
`include "graytobin.v"
module graytobin_tb();
reg[3:0]g;
wire[3:0]b;
graytobin gtb(g,b);
initial
begin
$dumpfile("graytobin_tb.vcd");
$dumpvars(0,graytobin_tb);
g=4'b0000;
#20;
g=4'b0001;
#20;
g=4'b0010;
#20;
g=4'b0011;
#20;
g=4'b0100;
#20;
g=4'b0101;
#20;
g=4'b0110;
#20;
g=4'b0111;
#20;
g=4'b1000;
#20;
g=4'b1001;
#20;
g=4'b1010;
#20;
g=4'b1011;
#20;
g=4'b1100;
#20;
g=4'b1101;
#20;
g=4'b1110;
#20;
g=4'b1111;
#20;
$display("Test Complete");
end
endmodule

Lab_5/graytobin_tb.vcd
$date
	Mon Sep  2 10:13:34 2024
$end
$version
	Icarus Verilog
$end
$timescale
	1ns
$end
$scope module graytobin_tb $end
$var wire 4 ! b [3:0] $end
$var reg 4 " g [3:0] $end
$scope module gtb $end
$var wire 4 # g [3:0] $end
$var wire 4 $ b [3:0] $end
$scope module m1 $end
$var wire 1 % in0 $end
$var wire 1 & in1 $end
$var wire 1 ' in2 $end
$var wire 1 ( in3 $end
$var wire 1 ) in4 $end
$var wire 1 * in5 $end
$var wire 1 + in6 $end
$var wire 1 , in7 $end
$var wire 3 - s [2:0] $end
$var reg 1 . out $end
$upscope $end
$scope module m2 $end
$var wire 1 / in0 $end
$var wire 1 0 in1 $end
$var wire 1 1 in2 $end
$var wire 1 2 in3 $end
$var wire 1 3 in4 $end
$var wire 1 4 in5 $end
$var wire 1 5 in6 $end
$var wire 1 6 in7 $end
$var wire 3 7 s [2:0] $end
$var reg 1 8 out $end
$upscope $end
$scope module m3 $end
$var wire 1 9 in0 $end
$var wire 1 : in1 $end
$var wire 1 ; in2 $end
$var wire 1 < in3 $end
$var wire 1 = in4 $end
$var wire 1 > in5 $end
$var wire 1 ? in6 $end
$var wire 1 @ in7 $end
$var wire 3 A s [2:0] $end
$var reg 1 B out $end
$upscope $end
$scope module m4 $end
$var wire 1 C in0 $end
$var wire 1 D in1 $end
$var wire 1 E in2 $end
$var wire 1 F in3 $end
$var wire 1 G in4 $end
$var wire 1 H in5 $end
$var wire 1 I in6 $end
$var wire 1 J in7 $end
$var wire 3 K s [2:0] $end
$var reg 1 L out $end
$upscope $end
$upscope $end
$upscope $end
$enddefinitions $end
#0
$dumpvars
0L
b0 K
1J
0I
0H
1G
0F
1E
1D
0C
0B
b0 A
1@
0?
0>
1=
0<
1;
1:
09
08
b0 7
06
05
14
13
12
11
00
0/
0.
b0 -
1,
1+
1*
1)
0(
0'
0&
0%
b0 $
b0 #
b0 "
b0 !
$end
#20
1B
0D
0E
0G
b10 !
b10 $
0L
0J
b1 -
b1 7
b1 A
b1 K
1C
1F
1H
1I
b1 "
b1 #
#40
1L
b111 !
b111 $
18
1D
1E
1G
1J
b10 -
b10 7
b10 A
b10 K
0C
0F
0H
0I
b10 "
b10 #
#60
b101 !
b101 $
0B
0D
0E
0G
0J
b11 -
b11 7
b11 A
b11 K
1C
1F
1H
1I
b11 "
b11 #
#80
1.
1B
1D
1E
1G
b1111 !
b1111 $
1L
1J
b100 -
b100 7
b100 A
b100 K
0C
0F
0H
0I
b100 "
b100 #
#100
b1101 !
b1101 $
0B
0D
0E
0G
0J
b101 -
b101 7
b101 A
b101 K
1C
1F
1H
1I
b101 "
b101 #
#120
08
1D
1E
1G
b1000 !
b1000 $
0L
1J
b110 -
b110 7
b110 A
b110 K
0C
0F
0H
0I
b110 "
b110 #
#140
b1010 !
b1010 $
1B
0D
0E
0G
0J
b111 -
b111 7
b111 A
b111 K
1C
1F
1H
1I
b111 "
b111 #
#160
0.
b0 !
b0 $
0B
1D
1E
1G
1J
b0 -
b0 7
b0 A
b0 K
0C
0F
0H
0I
b1000 "
b1000 #
#180
1B
0D
0E
0G
b10 !
b10 $
0L
0J
b1 -
b1 7
b1 A
b1 K
1C
1F
1H
1I
b1001 "
b1001 #
#200
1L
b111 !
b111 $
18
1D
1E
1G
1J
b10 -
b10 7
b10 A
b10 K
0C
0F
0H
0I
b1010 "
b1010 #
#220
b101 !
b101 $
0B
0D
0E
0G
0J
b11 -
b11 7
b11 A
b11 K
1C
1F
1H
1I
b1011 "
b1011 #
#240
1.
1B
1D
1E
1G
b1111 !
b1111 $
1L
1J
b100 -
b100 7
b100 A
b100 K
0C
0F
0H
0I
b1100 "
b1100 #
#260
b1101 !
b1101 $
0B
0D
0E
0G
0J
b101 -
b101 7
b101 A
b101 K
1C
1F
1H
1I
b1101 "
b1101 #
#280
08
1D
1E
1G
b1000 !
b1000 $
0L
1J
b110 -
b110 7
b110 A
b110 K
0C
0F
0H
0I
b1110 "
b1110 #
#300
b1010 !
b1010 $
1B
0D
0E
0G
0J
b111 -
b111 7
b111 A
b111 K
1C
1F
1H
1I
b1111 "
b1111 #
