Lab_5/majority_func.v
module decoder2to4(w,en,o);
input [1:0]w;
input en;
output reg[3:0]o;
always @(w,en)
begin
if(en==1)
begin
case(w)
0:o=1;
1:o=2;
2:o=4;
3:o=8;
endcase
end
else
begin
o=1'b0;
end
end
endmodule
module majority_func(in,y);
input[2:0] in;
output y;
wire[7:0]o;
decoder2to4 d1(in[1:0],~in[2],o[3:0]);
decoder2to4 d2(in[1:0],in[2],o[7:4]);
assign y=o[3]|o[5]|o[6]|o[7];
endmodule

Lab_5/majority_func_tb.v
`timescale 1ns/1ns
`include"majority_func.v"
module majority_func_tb();
reg [2:0]in;
wire y;
majority_func mfunc(in,y);
initial
begin
$dumpfile("majority_func_tb.vcd");
$dumpvars(0,majority_func_tb);
in=0;
#20;
in=1;
#20;
in=2;
#20;
in=3;
#20;
in=4;
#20;
in=5;
#20;
in=6;
#20;
in=7;
#20;
$display("Test complete");
end
endmodule

Lab_5/majority_func_tb.vcd
$date
	Mon Sep  2 10:46:02 2024
$end
$version
	Icarus Verilog
$end
$timescale
	1ns
$end
$scope module majority_func_tb $end
$var wire 1 ! y $end
$var reg 3 " in [2:0] $end
$scope module mfunc $end
$var wire 3 # in [2:0] $end
$var wire 1 ! y $end
$var wire 8 $ o [7:0] $end
$scope module d1 $end
$var wire 1 % en $end
$var wire 2 & w [1:0] $end
$var reg 4 ' o [3:0] $end
$upscope $end
$scope module d2 $end
$var wire 1 ( en $end
$var wire 2 ) w [1:0] $end
$var reg 4 * o [3:0] $end
$upscope $end
$upscope $end
$upscope $end
$enddefinitions $end
#0
$dumpvars
b0 *
b0 )
0(
b1 '
b0 &
1%
b1 $
b0 #
b0 "
0!
$end
#20
b10 $
b10 '
b1 &
b1 )
b1 "
b1 #
#40
b100 $
b100 '
b10 &
b10 )
b10 "
b10 #
#60
1!
b1000 $
b1000 '
b11 &
b11 )
b11 "
b11 #
#80
0!
b0 '
0%
b10000 $
b1 *
b0 &
b0 )
1(
b100 "
b100 #
#100
1!
b100000 $
b10 *
b1 &
b1 )
b101 "
b101 #
#120
b1000000 $
b100 *
b10 &
b10 )
b110 "
b110 #
#140
b10000000 $
b1000 *
b11 &
b11 )
b111 "
b111 #
