Lab_5/mux4to1.v
module mux4to1 (s,c,d,f);
 input [1:0]s;
 input c,d;
 output reg f;
 always @(*)begin
 case(s)
 0: f=~c|~d;
 1: f=~d;
 2: f=~c&d;
 3:f=~d;
 default f=1'b0;
 endcase 
 end
 endmodule

Lab_5/mux4to1_tb.v
`timescale 1ns/1ns
`include "mux4to1.v"
module mux4to1_tb();
 reg [1:0]s;
 reg c,d;
 wire f;
 mux4to1 m4to1 (s,c,d,f);
 initial
 begin
 $dumpfile("mux4to1_tb.vcd");
 $dumpvars(0,mux4to1_tb);
 s=2'b00; c=1'b0; d=1'b0;
 #20;
  s=2'b00; c=1'b0; d=1'b1;
 #20;
  s=2'b00; c=1'b1; d=1'b0;
 #20;
  s=2'b00; c=1'b1; d=1'b1;
 #20;
  s=2'b01; c=1'b0; d=1'b0;
 #20;
  s=2'b01; c=1'b0; d=1'b1;
 #20;
  s=2'b01; c=1'b1; d=1'b0;
 #20;
  s=2'b01; c=1'b1; d=1'b1;
  #20;
   s=2'b10; c=1'b0; d=1'b0;
 #20;
  s=2'b10; c=1'b0; d=1'b1;
 #20;
  s=2'b10; c=1'b1; d=1'b0;
 #20;
  s=2'b10; c=1'b1; d=1'b1;
  #20;
   s=2'b11; c=1'b0; d=1'b0;
 #20;
  s=2'b11; c=1'b0; d=1'b1;
 #20;
  s=2'b11; c=1'b1; d=1'b0;
 #20;
  s=2'b11; c=1'b1; d=1'b1;
  #20;
  $display("Test complete");
  end
  endmodule

Lab_5/mux4to1_tb.vcd
$date
	Mon Sep  2 09:50:20 2024
$end
$version
	Icarus Verilog
$end
$timescale
	1ns
$end
$scope module mux4to1_tb $end
$var wire 1 ! f $end
$var reg 1 " c $end
$var reg 1 # d $end
$var reg 2 $ s [1:0] $end
$scope module m4to1 $end
$var wire 1 " c $end
$var wire 1 # d $end
$var wire 2 % s [1:0] $end
$var reg 1 ! f $end
$upscope $end
$upscope $end
$enddefinitions $end
#0
$dumpvars
b0 %
b0 $
0#
0"
1!
$end
#20
1#
#40
0#
1"
#60
0!
1#
#80
1!
0#
0"
b1 $
b1 %
#100
0!
1#
#120
1!
0#
1"
#140
0!
1#
#160
0#
0"
b10 $
b10 %
#180
1!
1#
#200
0!
0#
1"
#220
1#
#240
1!
0#
0"
b11 $
b11 %
#260
0!
1#
#280
1!
0#
1"
#300
0!
1#
