Lab_5/orgate.v
module decoder(i,out);
input[3:0]i;
output reg [15:0] out;
always @(*) begin
case(i)
0:out=1;
1:out=2;
2:out=4;
3:out=8;
4:out=16;
5:out=32;
6:out=64;
7:out=128;
8:out=256;
9:out=512;
10:out=1024;
11:out=2048;
12:out=4096;
13:out=8192;
14:out=16384;
15:out=32768;
default: out=1'b0;
endcase
end
endmodule
module orgate(in,f);
input [3:0] in;
output f;
wire [15:0]out;
decoder gt(in[3:0],out[15:0]);
assign f=out[2]|out[3]|out[4]|out[5]|out[6]|out[7]|out[10]|out[11]|out[12]|out[15];
endmodule

Lab_5/orgate_tb.v
`timescale 1ns/1ns
`include"orgate.v"
module orgate_tb;
reg[3:0] in;
wire f;
orgate og(in,f);
initial
begin
$dumpfile("orgate_tb.vcd");
$dumpvars(0,orgate_tb);
in=0;
#20;
in=1;
#20;
in=2;
#20;
in=3;
#20;
in=4;
#20;
in=5;
#20;
in=6;
#20;
in=7;
#20;
in=8;
#20;
in=9;
#20;
in=10;
#20;
in=11;
#20;
in=12;
#20;
in=13;
#20;
in=14;
#20;
in=15;
#20;
$display("Test complete");
end
endmodule

Lab_5/orgate_tb.vcd
$date
	Mon Sep  2 10:35:47 2024
$end
$version
	Icarus Verilog
$end
$timescale
	1ns
$end
$scope module orgate_tb $end
$var wire 1 ! f $end
$var reg 4 " in [3:0] $end
$scope module og $end
$var wire 1 ! f $end
$var wire 4 # in [3:0] $end
$var wire 16 $ out [15:0] $end
$scope module gt $end
$var wire 4 % i [3:0] $end
$var reg 16 & out [15:0] $end
$upscope $end
$upscope $end
$upscope $end
$enddefinitions $end
#0
$dumpvars
b1 &
b0 %
b1 $
b0 #
b0 "
0!
$end
#20
b10 $
b10 &
b1 "
b1 #
b1 %
#40
1!
b100 $
b100 &
b10 "
b10 #
b10 %
#60
b1000 $
b1000 &
b11 "
b11 #
b11 %
#80
b10000 $
b10000 &
b100 "
b100 #
b100 %
#100
b100000 $
b100000 &
b101 "
b101 #
b101 %
#120
b1000000 $
b1000000 &
b110 "
b110 #
b110 %
#140
b10000000 $
b10000000 &
b111 "
b111 #
b111 %
#160
0!
b100000000 $
b100000000 &
b1000 "
b1000 #
b1000 %
#180
b1000000000 $
b1000000000 &
b1001 "
b1001 #
b1001 %
#200
1!
b10000000000 $
b10000000000 &
b1010 "
b1010 #
b1010 %
#220
b100000000000 $
b100000000000 &
b1011 "
b1011 #
b1011 %
#240
b1000000000000 $
b1000000000000 &
b1100 "
b1100 #
b1100 %
#260
0!
b10000000000000 $
b10000000000000 &
b1101 "
b1101 #
b1101 %
#280
b100000000000000 $
b100000000000000 &
b1110 "
b1110 #
b1110 %
#300
1!
b1000000000000000 $
b1000000000000000 &
b1111 "
b1111 #
b1111 %
