Lab_2/ex1.v
module ex1(A,B,C,D,F);
  input A,B,C,D;
  output F;
  assign g=(A & B);
  assign h=(C|D);
  assign F=(g & h)|(~g & ~h);
endmodule

Lab_2/ex1_tb.v
`timescale 1ns/1ns
`include "ex1.v"

module ex1_tb();
reg A,B,C,D;
wire F;

ex1 ex(A,B,C,D,F);
initial 
begin

  $dumpfile("ex1.vcd");
  $dumpvars(0,ex1_tb);
  
    A=1'b0; B=1'b0; C=1'b0;D=1'b0;
    #20;
    
    A=1'b0; B=1'b0; C=1'b0;D=1'b1;
    #20;
    
    A=1'b0; B=1'b0; C=1'b1;D=1'b0;
    #20;
    
    A=1'b0; B=1'b0; C=1'b1;D=1'b1;
    #20;
    
    A=1'b0; B=1'b1; C=1'b0;D=1'b0;
    #20;
    
    A=1'b0; B=1'b1; C=1'b0;D=1'b1;
    #20;
    
  A=1'b0; B=1'b1; C=1'b1;D=1'b0;
    #20;
    
    A=1'b0; B=1'b1; C=1'b1;D=1'b1;
    #20;
    
   A=1'b1; B=1'b0; C=1'b0;D=1'b0;
    #20;
    
   A=1'b1;B=1'b0; C=1'b0;D=1'b1;
    #20;
    
   A=1'b1; B=1'b0; C=1'b1;D=1'b0;
    #20;
    
   A=1'b1; B=1'b0; C=1'b1;D=1'b1;
    #20;
    
   
    
     A=1'b1; B=1'b1; C=1'b0;D=1'b0;
    #20;
    
     A=1'b1; B=1'b1; C=1'b0;D=1'b1;
    #20;
    
     A=1'b1; B=1'b1; C=1'b1;D=1'b0;
    #20;
    
     A=1'b1; B=1'b1; C=1'b1;D=1'b1;
    #20;
    
    $display("Test complete");
  
end

endmodule

Lab_2/ex1.vcd
$date
	Sat Aug 10 09:46:08 2024
$end
$version
	Icarus Verilog
$end
$timescale
	1ns
$end
$scope module ex1_tb $end
$var wire 1 ! F $end
$var reg 1 " A $end
$var reg 1 # B $end
$var reg 1 $ C $end
$var reg 1 % D $end
$scope module ex $end
$var wire 1 " A $end
$var wire 1 # B $end
$var wire 1 $ C $end
$var wire 1 % D $end
$var wire 1 ! F $end
$var wire 1 & g $end
$var wire 1 ' h $end
$upscope $end
$upscope $end
$enddefinitions $end
#0
$dumpvars
0'
0&
0%
0$
0#
0"
1!
$end
#20
0!
1'
1%
#40
0%
1$
#60
1%
#80
1!
0'
0%
0$
1#
#100
0!
1'
1%
#120
0%
1$
#140
1%
#160
1!
0'
0%
0$
0#
1"
#180
0!
1'
1%
#200
0%
1$
#220
1%
#240
0'
1&
0%
0$
1#
#260
1!
1'
1%
#280
0%
1$
#300
1%
