Lab_2/full_adder.v
module full_adder(A,B,Cin,sum,carry);
 input A,B,Cin;
 output sum,carry;
 assign sum=A^B^Cin;
 assign carry=(A & B)|(B & Cin)|(Cin & A);
endmodule

Lab_2/full_adder_tb.v
`timescale 1ns/1ns
`include "full_adder.v"

module full_adder_tb();
reg A,B,Cin;
wire sum,carry;

full_adder ex(A,B,Cin, sum, carry);
initial 
begin

  $dumpfile("full_adder.vcd");
  $dumpvars(0,full_adder_tb);
  
    A=1'b0; B=1'b0; Cin=1'b0;
    #20;
    
    A=1'b0; B=1'b0; Cin=1'b1;
    #20;
    
    A=1'b0; B=1'b1; Cin=1'b0;
    #20;
    
     A=1'b0; B=1'b1; Cin=1'b1;
    #20;
    
    A=1'b1; B=1'b0; Cin=1'b0;
    #20;
    
    A=1'b1; B=1'b0; Cin=1'b1;
    #20;
    
    A=1'b1; B=1'b1; Cin=1'b0;
    #20;
    
    A=1'b1; B=1'b1; Cin=1'b1;
    #20;
   
    
   
   
   
    $display("Test complete");
  
end

endmodule

Lab_2/full_adder.vcd
$date
	Sat Aug 10 10:10:47 2024
$end
$version
	Icarus Verilog
$end
$timescale
	1ns
$end
$scope module full_adder_tb $end
$var wire 1 ! sum $end
$var wire 1 " carry $end
$var reg 1 # A $end
$var reg 1 $ B $end
$var reg 1 % Cin $end
$scope module ex $end
$var wire 1 # A $end
$var wire 1 $ B $end
$var wire 1 % Cin $end
$var wire 1 " carry $end
$var wire 1 ! sum $end
$upscope $end
$upscope $end
$enddefinitions $end
#0
$dumpvars
0%
0$
0#
0"
0!
$end
#20
1!
1%
#40
0%
1$
#60
1"
0!
1%
#80
0"
1!
0%
0$
1#
#100
1"
0!
1%
#120
0%
1$
#140
1!
1%
