Lab_1/A3.v
module A3(A,B,C,D,F);
   input A,B,C,D;
   output F;
   assign F=(B & C & D)|(A & C & D)|(C & A & B)+ (D & A & B);
   
   
   
   

   
endmodule

Lab_1/A3_tb.v
`timescale 1ns/1ns
`include "A3.v"

module A3_tb();
reg A,B,C,D;
wire F;

A3 ex(A,B,C,D,F);
initial 
begin

  $dumpfile("A3.vcd");
  $dumpvars(0,A3_tb);
  
    A=1'b0; B=1'b0; C=1'b0;D=1'b0;
    #20;
    
    A=1'b0; B=1'b0; C=1'b0;D=1'b1;
    #20;
    
    A=1'b0; B=1'b0; C=1'b1;D=1'b0;
    #20;
    
    A=1'b0; B=1'b0; C=1'b1;D=1'b1;
    #20;
    
    A=1'b0; B=1'b1; C=1'b0;D=1'b0;
    #20;
    
    A=1'b0; B=1'b1; C=1'b0;D=1'b1;
    #20;
    
  A=1'b0; B=1'b1; C=1'b1;D=1'b0;
    #20;
    
    A=1'b0; B=1'b1; C=1'b1;D=1'b1;
    #20;
    
   A=1'b1; B=1'b0; C=1'b0;D=1'b0;
    #20;
    
   A=1'b1;B=1'b0; C=1'b0;D=1'b1;
    #20;
    
   A=1'b1; B=1'b0; C=1'b1;D=1'b0;
    #20;
    
   A=1'b1; B=1'b0; C=1'b1;D=1'b1;
    #20;
    
   
    
     A=1'b1; B=1'b1; C=1'b0;D=1'b0;
    #20;
    
     A=1'b1; B=1'b1; C=1'b0;D=1'b1;
    #20;
    
     A=1'b1; B=1'b1; C=1'b1;D=1'b0;
    #20;
    
     A=1'b1; B=1'b1; C=1'b1;D=1'b1;
    #20;
    
    $display("Test complete");
  
end

endmodule

Lab_1/A3.vcd
$date
	Sat Aug  3 10:41:25 2024
$end
$version
	Icarus Verilog
$end
$timescale
	1ns
$end
$scope module A3_tb $end
$var wire 1 ! F $end
$var reg 1 " A $end
$var reg 1 # B $end
$var reg 1 $ C $end
$var reg 1 % D $end
$scope module ex $end
$var wire 1 " A $end
$var wire 1 # B $end
$var wire 1 $ C $end
$var wire 1 % D $end
$var wire 1 ! F $end
$upscope $end
$upscope $end
$enddefinitions $end
#0
$dumpvars
0%
0$
0#
0"
0!
$end
#20
1%
#40
0%
1$
#60
1%
#80
0%
0$
1#
#100
1%
#120
0%
1$
#140
1!
1%
#160
0!
0%
0$
0#
1"
#180
1%
#200
0%
1$
#220
1!
1%
#240
0!
0%
0$
1#
#260
1!
1%
#280
0%
1$
#300
1%
