Lab_1/ex1a.v
module ex1a(A,B,C,D,F);
   input A,B,C,D;
   output F;
   assign F=(~A & ~B)|(~C & ~D)|(~C & ~B);
endmodule

Lab_1/ex1a_tb.v
`timescale 1ns/1ns
`include "ex1a.v"

module ex1a_tb();
reg A,B,C,D;
wire F;

ex1a ex(A,B,C,D,F);
initial 
begin

  $dumpfile("ex1a.vcd");
  $dumpvars(0,ex1a_tb);
  
    A=1'b0; B=1'b0; C=1'b0;D=1'b0;
    #20;
    
    A=1'b0; B=1'b0; C=1'b0;D=1'b1;
    #20;
    
    A=1'b0; B=1'b0; C=1'b1;D=1'b0;
    #20;
    
    A=1'b0; B=1'b0; C=1'b1;D=1'b1;
    #20;
    
    A=1'b0; B=1'b1; C=1'b0;D=1'b0;
    #20;
    
    A=1'b0; B=1'b1; C=1'b0;D=1'b1;
    #20;
    
  A=1'b0; B=1'b1; C=1'b1;D=1'b0;
    #20;
    
    A=1'b0; B=1'b1; C=1'b1;D=1'b1;
    #20;
    
   A=1'b1; B=1'b0; C=1'b0;D=1'b0;
    #20;
    
   A=1'b1;B=1'b0; C=1'b0;D=1'b1;
    #20;
    
   A=1'b1; B=1'b0; C=1'b1;D=1'b0;
    #20;
    
   A=1'b1; B=1'b0; C=1'b1;D=1'b1;
    #20;
    
   
    
     A=1'b1; B=1'b1; C=1'b0;D=1'b0;
    #20;
    
     A=1'b1; B=1'b1; C=1'b0;D=1'b1;
    #20;
    
     A=1'b1; B=1'b1; C=1'b1;D=1'b0;
    #20;
    
     A=1'b1; B=1'b1; C=1'b1;D=1'b1;
    #20;
    
    $display("Test complete");
  
end

endmodule

Lab_1/ex1a.vcd
$date
	Sat Aug  3 09:50:42 2024
$end
$version
	Icarus Verilog
$end
$timescale
	1ns
$end
$scope module ex1a_tb $end
$var wire 1 ! F $end
$var reg 1 " A $end
$var reg 1 # B $end
$var reg 1 $ C $end
$var reg 1 % D $end
$scope module ex $end
$var wire 1 " A $end
$var wire 1 # B $end
$var wire 1 $ C $end
$var wire 1 % D $end
$var wire 1 ! F $end
$upscope $end
$upscope $end
$enddefinitions $end
#0
$dumpvars
0%
0$
0#
0"
1!
$end
#20
1%
#40
0%
1$
#60
1%
#80
0%
0$
1#
#100
0!
1%
#120
0%
1$
#140
1%
#160
1!
0%
0$
0#
1"
#180
1%
#200
0!
0%
1$
#220
1%
#240
1!
0%
0$
1#
#260
0!
1%
#280
0%
1$
#300
1%
