Lab_1/Lab1_example.v
module Lab1_example(x1,x2,x3,x4,f);
   input x1,x2,x3,x4;
   output f;
   assign f=(x2 & ~x3)|(x3 & ~x4);
endmodule

Lab_1/Lab1_example_tb.v
`timescale 1ns/1ns
`include "Lab1_example.v"

module Lab1_example_tb();
reg x1,x2,x3,x4;
wire f;

Lab1_example ex(x1,x2,x3,x4,f);
initial 
begin

  $dumpfile("Lab1_example.vcd");
  $dumpvars(0,Lab1_example_tb);
  
    x1=1'b0; x2=1'b0; x3=1'b0;x4=1'b0;
    #20;
    
    x1=1'b0; x2=1'b0; x3=1'b0;x4=1'b1;
    #20;
    
    x1=1'b0; x2=1'b0; x3=1'b1;x4=1'b0;
    #20;
    
    x1=1'b0; x2=1'b0; x3=1'b1;x4=1'b1;
    #20;
    
    x1=1'b0; x2=1'b1; x3=1'b0;x4=1'b0;
    #20;
    
    x1=1'b0; x2=1'b1; x3=1'b0;x4=1'b1;
    #20;
    
    x1=1'b0; x2=1'b1; x3=1'b1;x4=1'b0;
    #20;
    
    x1=1'b0; x2=1'b1; x3=1'b1;x4=1'b1;
    #20;
    
    x1=1'b1; x2=1'b0; x3=1'b0;x4=1'b0;
    #20;
    
    x1=1'b1; x2=1'b0; x3=1'b0;x4=1'b1;
    #20;
    
    x1=1'b1; x2=1'b0; x3=1'b1;x4=1'b0;
    #20;
    
    x1=1'b1; x2=1'b0; x3=1'b1;x4=1'b1;
    #20;
    
   
    
     x1=1'b1; x2=1'b1; x3=1'b0;x4=1'b0;
    #20;
    
     x1=1'b1; x2=1'b1; x3=1'b0;x4=1'b1;
    #20;
    
     x1=1'b1; x2=1'b1; x3=1'b1;x4=1'b0;
    #20;
    
     x1=1'b1; x2=1'b1; x3=1'b1;x4=1'b1;
    #20;
    
    $display("Test complete");
  
end

endmodule

Lab_1/Lab1_example.vcd
$date
	Sat Aug  3 09:30:44 2024
$end
$version
	Icarus Verilog
$end
$timescale
	1ns
$end
$scope module Lab1_example_tb $end
$var wire 1 ! f $end
$var reg 1 " x1 $end
$var reg 1 # x2 $end
$var reg 1 $ x3 $end
$var reg 1 % x4 $end
$scope module ex $end
$var wire 1 ! f $end
$var wire 1 " x1 $end
$var wire 1 # x2 $end
$var wire 1 $ x3 $end
$var wire 1 % x4 $end
$upscope $end
$upscope $end
$enddefinitions $end
#0
$dumpvars
0%
0$
0#
0"
0!
$end
#20
1%
#40
1!
0%
1$
#60
0!
1%
#80
1!
0%
0$
1#
#100
1%
#120
0%
1$
#140
0!
1%
#160
0%
0$
0#
1"
#180
1%
#200
1!
0%
1$
#220
0!
1%
#240
1!
0%
0$
1#
#260
1%
#280
0%
1$
#300
0!
1%
