Lab_4/priority_enc_4to2.v
module priority_enc_4to2(in,en,out);
 input [3:0]in;
 input en;
 output reg[1:0] out;
 always @(in,en)
 begin
 if(en==1)
 begin
 casex(in)
  4'b1xxx: out=2'b11;
  4'b01xx: out=2'b10;
  4'b001x:out=2'b01;
  4'b0001:out=2'b00;
 endcase
 end
 else
 begin
 out=2'b00;
 end
 end
 endmodule

Lab_4/priority_enc_4to2_tb.v
`timescale 1ns/1ns
`include "priority_enc_4to2.v"
module priority_enc_4to2_tb();
reg [3:0]in;
reg EN;
wire [1:0]out;
priority_enc_4to2 p_enc4to2(in,EN,out);
initial
begin
$dumpfile("priority_enc_4to2_tb.vcd");
$dumpvars(0,priority_enc_4to2_tb);
EN=1'b0;in=4'b0001;
#20;
EN=1'b0;in=4'b1001;
#20;
EN=1'b1;in=4'b0001;
#20;
EN=1'b1;in=4'b0101;
#20;
EN=1'b1;in=4'b1111;
#20;
EN=1'b1;in=4'b0011;
#20;
EN=1'b1;in=4'b1010;
#20;
EN=1'b1;in=4'b1110;
#20;
$display("Test complete");
end
endmodule

Lab_4/priority_enc_4to2_tb.vcd
$date
	Sat Aug 31 10:26:42 2024
$end
$version
	Icarus Verilog
$end
$timescale
	1ns
$end
$scope module priority_enc_4to2_tb $end
$var wire 2 ! out [1:0] $end
$var reg 1 " EN $end
$var reg 4 # in [3:0] $end
$scope module p_enc4to2 $end
$var wire 1 " en $end
$var wire 4 $ in [3:0] $end
$var reg 2 % out [1:0] $end
$upscope $end
$upscope $end
$enddefinitions $end
#0
$dumpvars
b0 %
b1 $
b1 #
0"
b0 !
$end
#20
b1001 #
b1001 $
#40
b1 #
b1 $
1"
#60
b10 !
b10 %
b101 #
b101 $
#80
b11 !
b11 %
b1111 #
b1111 $
#100
b1 !
b1 %
b11 #
b11 $
#120
b11 !
b11 %
b1010 #
b1010 $
#140
b1110 #
b1110 $
